django_formset-2.2.3.dist-info/licenses/LICENSE
formset/__init__.py
formset/admin.py
formset/boundfield.py
formset/calendar.py
formset/collection.py
formset/dialog.py
formset/exceptions.py
formset/fieldset.py
formset/fieldsmapping.py
formset/forms.py
formset/stepper.py
formset/upload.py
formset/utils.py
formset/validators.py
formset/views.py
formset/formfields/__init__.py
formset/formfields/activator.py
formset/formfields/collection.py
formset/formfields/ranges.py
formset/formfields/richtext.py
formset/formfields/shadow.py
formset/locale/af/LC_MESSAGES/djangojs.mo
formset/locale/af/LC_MESSAGES/djangojs.po
formset/locale/ar/LC_MESSAGES/djangojs.mo
formset/locale/ar/LC_MESSAGES/djangojs.po
formset/locale/bg/LC_MESSAGES/djangojs.mo
formset/locale/bg/LC_MESSAGES/djangojs.po
formset/locale/ca/LC_MESSAGES/djangojs.mo
formset/locale/ca/LC_MESSAGES/djangojs.po
formset/locale/cs/LC_MESSAGES/djangojs.mo
formset/locale/cs/LC_MESSAGES/djangojs.po
formset/locale/da/LC_MESSAGES/djangojs.mo
formset/locale/da/LC_MESSAGES/djangojs.po
formset/locale/de/LC_MESSAGES/django.mo
formset/locale/de/LC_MESSAGES/django.po
formset/locale/de/LC_MESSAGES/djangojs.mo
formset/locale/de/LC_MESSAGES/djangojs.po
formset/locale/el/LC_MESSAGES/djangojs.mo
formset/locale/el/LC_MESSAGES/djangojs.po
formset/locale/eo/LC_MESSAGES/djangojs.mo
formset/locale/eo/LC_MESSAGES/djangojs.po
formset/locale/es/LC_MESSAGES/djangojs.mo
formset/locale/es/LC_MESSAGES/djangojs.po
formset/locale/et/LC_MESSAGES/djangojs.mo
formset/locale/et/LC_MESSAGES/djangojs.po
formset/locale/eu/LC_MESSAGES/djangojs.mo
formset/locale/eu/LC_MESSAGES/djangojs.po
formset/locale/eu_ES/LC_MESSAGES/djangojs.mo
formset/locale/eu_ES/LC_MESSAGES/djangojs.po
formset/locale/fa/LC_MESSAGES/djangojs.mo
formset/locale/fa/LC_MESSAGES/djangojs.po
formset/locale/fi/LC_MESSAGES/djangojs.mo
formset/locale/fi/LC_MESSAGES/djangojs.po
formset/locale/fr/LC_MESSAGES/djangojs.mo
formset/locale/fr/LC_MESSAGES/djangojs.po
formset/locale/he/LC_MESSAGES/djangojs.mo
formset/locale/he/LC_MESSAGES/djangojs.po
django_formset-2.2.3.dist-info/METADATA
django_formset-2.2.3.dist-info/WHEEL
django_formset-2.2.3.dist-info/top_level.txt
django_formset-2.2.3.dist-info/RECORD
